ldap_auth_provider.py
matrix_synapse_ldap3-0.3.0.dist-info/LICENSE
matrix_synapse_ldap3-0.3.0.dist-info/METADATA
matrix_synapse_ldap3-0.3.0.dist-info/WHEEL
matrix_synapse_ldap3-0.3.0.dist-info/top_level.txt
matrix_synapse_ldap3-0.3.0.dist-info/RECORD
