Metadata-Version: 2.1
Name: matrix-synapse-ldap3
Version: 0.3.0
Summary: An LDAP3 auth provider for Synapse
Home-page: https://github.com/matrix-org/matrix-synapse-ldap3
Classifier: Development Status :: 4 - Beta
Classifier: License :: OSI Approved :: Apache Software License
Classifier: Programming Language :: Python :: 3 :: Only
Requires-Python: >=3.7
License-File: LICENSE
Requires-Dist: Twisted>=15.1.0
Requires-Dist: ldap3>=2.8
Requires-Dist: service_identity
Provides-Extra: dev
Requires-Dist: matrix-synapse; extra == "dev"
Requires-Dist: tox; extra == "dev"
Requires-Dist: ldaptor; extra == "dev"
Requires-Dist: mypy==0.910; extra == "dev"
Requires-Dist: types-setuptools; extra == "dev"
Requires-Dist: black==22.3.0; extra == "dev"
Requires-Dist: flake8==4.0.1; extra == "dev"
Requires-Dist: isort==5.9.3; extra == "dev"
